CHANGES.txt
DEPENDENCES.txt
README.txt
setup.py
src/__init__.py
src/ng/__init__.py
src/ng.content.profile.egg-info/PKG-INFO
src/ng.content.profile.egg-info/SOURCES.txt
src/ng.content.profile.egg-info/dependency_links.txt
src/ng.content.profile.egg-info/namespace_packages.txt
src/ng.content.profile.egg-info/not-zip-safe
src/ng.content.profile.egg-info/requires.txt
src/ng.content.profile.egg-info/top_level.txt
src/ng/content/__init__.py
src/ng/content/profile/__init__.py
src/ng/content/profile/configure.zcml
src/ng/content/profile/ng.content.profile.txt
src/ng/content/profile/communityobjectqueueannotation/__init__.py
src/ng/content/profile/communityobjectqueueannotation/communityobjectqueueannotationableadapter.py
src/ng/content/profile/communityobjectqueueannotation/configure.zcml
src/ng/content/profile/communityobjectqueueannotation/interfaces.py
src/ng/content/profile/communityobjectqueueannotation/browser/__init__.py
src/ng/content/profile/communityobjectqueueannotation/browser/configure.zcml
src/ng/content/profile/etc/ng.content.profile-configure.zcml
src/ng/content/profile/exchangeannotation/__init__.py
src/ng/content/profile/exchangeannotation/configure.zcml
src/ng/content/profile/exchangeannotation/exchange.py
src/ng/content/profile/exchangeannotation/exchangeannotationableadapter.py
src/ng/content/profile/exchangeannotation/interfaces.py
src/ng/content/profile/exchangeannotation/mailbox.py
src/ng/content/profile/exchangeannotation/message.py
src/ng/content/profile/exchangeannotation/browser/__init__.py
src/ng/content/profile/exchangeannotation/browser/configure.zcml
src/ng/content/profile/exchangeannotation/browser/messageadd.py
src/ng/content/profile/friendobjectqueueannotation/__init__.py
src/ng/content/profile/friendobjectqueueannotation/configure.zcml
src/ng/content/profile/friendobjectqueueannotation/friendobjectqueueannotation.py
src/ng/content/profile/friendobjectqueueannotation/friendobjectqueueannotationableadapter.py
src/ng/content/profile/friendobjectqueueannotation/friendobjectqueuehandler.py
src/ng/content/profile/friendobjectqueueannotation/friendshipadapter.py
src/ng/content/profile/friendobjectqueueannotation/interfaces.py
src/ng/content/profile/friendobjectqueueannotation/browser/__init__.py
