Metadata-Version: 1.0
Name: ng.content.profile
Version: 0.0.4
Summary: This product intendent to work with users profile
Home-page: http://www.dreambot.ru/DreamBotZope3Releases/ng.content.profile
Author: Andrey Orlov
Author-email: dbdt@dreambot.ru
License: GPL v2.1
Platform: UNKNOWN
Classifier: Environment :: Web Environment
Classifier: Intended Audience :: Developers
Classifier: License :: OSI Approved :: GNU General Public License (GPL)
Classifier: Programming Language :: Python
Classifier: Operating System :: OS Independent
Classifier: Topic :: Internet :: WWW/HTTP
Classifier: Framework :: Zope3
